Terran Command Center
Terran Supply Depot
Terran Command Center
Terran Barracks
Terran Supply Depot
Terran Marine
Terran Factory
Terran Supply Depot
Terran Factory
Terran Machine Shop
Terran Armory
Terran Siege Tank Tank Mode
Terran Supply Depot
Terran Machine Shop
Terran Academy
Terran Supply Depot
Terran Siege Tank Tank Mode
Terran Siege Tank Tank Mode
Terran Marine
Terran Supply Depot
Terran Supply Depot
Terran Goliath
Terran Comsat Station
Terran Comsat Station
Terran Starport
Terran Goliath
Terran Goliath
Terran Supply Depot
Terran Supply Depot
