Terran Command Center
Terran Supply Depot
Terran Barracks
Terran Supply Depot
Terran Marine
Terran Factory
Terran Command Center
Terran Vulture
Terran Supply Depot
Terran Machine Shop
Terran Factory
Terran Vulture
Terran Factory
Terran Vulture
Terran Vulture
Terran Vulture
Terran Supply Depot
Terran Engineering Bay
Terran Vulture
Terran Vulture
Terran Vulture
Terran Supply Depot
Terran Vulture
Terran Factory
Terran Vulture
Terran Vulture
Terran Vulture
Terran Supply Depot
Terran Vulture
Terran Vulture
Terran Supply Depot
Terran Supply Depot
Terran Factory
Terran Vulture
Terran Vulture
Terran Vulture
Terran Vulture
Terran Supply Depot
Terran Vulture
Terran Vulture
Terran Vulture
