Terran Command Center
Terran Supply Depot
Terran Barracks
Terran Supply Depot
Terran Marine
Terran Marine
Terran Command Center
Terran Marine
Terran Supply Depot
Terran Marine
Terran Supply Depot
Terran Factory
Terran Factory
Terran Factory
Terran Machine Shop
Terran Vulture
Terran Armory
Terran Vulture
Terran Engineering Bay
Terran Vulture
Terran Supply Depot
Terran Vulture
Terran Vulture
Terran Vulture
Terran Supply Depot
Terran Factory
Terran Factory
Terran Vulture
Terran Vulture
Terran Vulture
Terran Supply Depot
Terran Missile Turret
Terran Missile Turret
Terran Supply Depot
Terran Goliath
Terran Academy
Terran Supply Depot
Terran Missile Turret
