Terran Command Center
Terran Supply Depot
Terran Barracks
Terran Supply Depot
Terran Factory
Terran Marine
Terran Command Center
Terran Vulture
Terran Supply Depot
Terran Vulture
Terran Factory
Terran Vulture
Terran Machine Shop
Terran Vulture
Terran Factory
Terran Vulture
Terran Vulture
Terran Supply Depot
Terran Factory
Terran Vulture
Terran Vulture
Terran Supply Depot
Terran Vulture
Terran Vulture
Terran Vulture
Terran Supply Depot
Terran Supply Depot
Terran Vulture
Terran Vulture
Terran Vulture
Terran Supply Depot
Terran Supply Depot
Terran Vulture
Terran Vulture
Terran Vulture
Terran Vulture
Terran Vulture
Terran Vulture
